bqpackage/__init__.py
bqpackage/chromedriver.exe
bqpackage/selenium_test.py
bqpackage/general/__init__.py
bqpackage/general/constants.py
bqpackage/playground/__init__.py
bqpackage/playground/test_play.py
bqpackage/rest_api/__init__.py
bqpackage/rest_api/request_actions.py
bqpackage/rest_api/utilities.py
bqpackage/selenium_base/__init__.py
bqpackage/selenium_base/selenium_actions.py
bqpackage/selenium_base/selenium_config.py
bqpackage/selenium_base/selenium_storage.py
bqpackage/shared/__init__.py
bqpackage/shared/db_mysql_capabilities.py
bqpackage/shared/run_parallel.py
bqpackage/shared/shared_utilities.py
bqpackage/unit_tests/__init__.py
bqpackage/unit_tests/actions_unit_test.py
bqpackage/unit_tests/api_unit_test.py
bqpackage/unit_tests/selenium_driver_unit_test.py
bqpackage-2.3.32.dist-info/LICENCE
bqpackage-2.3.32.dist-info/METADATA
bqpackage-2.3.32.dist-info/WHEEL
bqpackage-2.3.32.dist-info/top_level.txt
bqpackage-2.3.32.dist-info/RECORD
