Metadata-Version: 2.1
Name: bqpackage
Version: 2.3.32
Summary: Automation infrastructure kit tools for GUI and API tests
Home-page: https://upload.pypi.org/legacy/
Author: Moshe Sar-Idan
License: MIT
Classifier: Programming Language :: Python :: 3
Classifier: License :: OSI Approved :: MIT License
Classifier: Operating System :: OS Independent
Requires-Python: >=3.7
License-File: LICENCE
